peng_tool/__init__.py
peng_tool/peng_tool.py
peng_tool-0.3.0.dist-info/METADATA
peng_tool-0.3.0.dist-info/WHEEL
peng_tool-0.3.0.dist-info/top_level.txt
peng_tool-0.3.0.dist-info/RECORD
